README
setup.py
django_pubsubpull.egg-info/PKG-INFO
django_pubsubpull.egg-info/SOURCES.txt
django_pubsubpull.egg-info/dependency_links.txt
django_pubsubpull.egg-info/requires.txt
django_pubsubpull.egg-info/top_level.txt
pubsubpull/__init__.py
pubsubpull/admin.py
pubsubpull/api.py
pubsubpull/async.py
pubsubpull/fields.py
pubsubpull/middleware.py
pubsubpull/migrate.py
pubsubpull/models.py
pubsubpull/slumber_server.py
pubsubpull/trigger-attach.sql
pubsubpull/trigger-function.sql
pubsubpull/migrations/0001_initial.py
pubsubpull/migrations/0002_auto_20150513_0130.py
pubsubpull/migrations/0003_auto_20150512_0723.py
pubsubpull/migrations/0004_auto_20150520_1041.py
pubsubpull/migrations/0005_auto_20150520_1121.py
pubsubpull/migrations/0006_request_status.py
pubsubpull/migrations/0007_changesubscription.py
pubsubpull/migrations/__init__.py
pubsubpull/operations/__init__.py
pubsubpull/south_migrations/0001_initial.py
pubsubpull/south_migrations/0002_auto__del_subscription__add_updatelog__add_request.py
pubsubpull/south_migrations/0003_trigger_function.py
pubsubpull/south_migrations/0004_auto__add_field_request_method__add_field_request_path.py
pubsubpull/south_migrations/0005_auto__add_field_request_started__add_field_request_duration.py
pubsubpull/south_migrations/0006_auto__add_field_request_status.py
pubsubpull/south_migrations/0007_auto__add_changesubscription.py
pubsubpull/south_migrations/__init__.py
pubsubpull/tests/__init__.py
pubsubpull/tests/test_api.py
pubsubpull/tests/test_config.py
pubsubpull/tests/test_middleware.py
pubsubpull/tests/test_pull.py
pubsubpull/tests/test_trigger.py