Metadata-Version: 1.1
Name: django-pubsubpull
Version: 0.1.2
Summary: Pub/sub and pull for Django
Home-page: https://github.com/KayEss/django-pubsubpull
Author: Kirit Saelensminde
Author-email: kirit@felspar.com
License: Boost Software License - Version 1.0 - August 17th, 2003
Keywords: django rest data pub-sub pull
Platform: UNKNOWN
Classifier: Development Status :: 3 - Alpha
Classifier: Framework :: Django
Classifier: Intended Audience :: Developers
Classifier: Programming Language :: Python
Classifier: Topic :: Software Development :: Libraries :: Python Modules
Classifier: License :: OSI Approved
